althiqa/__init__.py
althiqa/aiirw.py
althiqa/althiqa_lib.py
althiqa/default_metrics.py
althiqa/utils.py
althiqa-0.0.6.dist-info/LICENSE
althiqa-0.0.6.dist-info/METADATA
althiqa-0.0.6.dist-info/WHEEL
althiqa-0.0.6.dist-info/top_level.txt
althiqa-0.0.6.dist-info/RECORD
