Metadata-Version: 2.1
Name: althiqa
Version: 0.0.6
Summary: althiqa API: the AI reporting and communication tool
Author-email: althiqa <info@althiqa.io>
License: Copyright (c) 2018 The Python Packaging Authority        
Project-URL: Homepage, https://github.com/althiqa/althiqa_lib
Project-URL: Bug Tracker, https://github.com/althiqa/althiqa_lib/issues
Classifier: Programming Language :: Python :: 3
Classifier: License :: OSI Approved :: MIT License
Classifier: Operating System :: OS Independent
Requires-Python: >=3.8
License-File: LICENSE
